README.md
fsst.py
setup.py
fsst.egg-info/PKG-INFO
fsst.egg-info/SOURCES.txt
fsst.egg-info/dependency_links.txt
fsst.egg-info/entry_points.txt
fsst.egg-info/not-zip-safe
fsst.egg-info/requires.txt
fsst.egg-info/top_level.txt