Metadata-Version: 2.1
Name: fsst
Version: 0.6.7
Summary: Fluree Schema Scenario Tool
Home-page: https://github.com/pibara/fluree-schema-scenario-tool
Author: Rob Meijer
Author-email: pibara@gmail.com
License: BSD
Keywords: flureedb fluree flureeql
Platform: UNKNOWN
Classifier: Development Status :: 5 - Production/Stable
Classifier: Environment :: Console
Classifier: Intended Audience :: Developers
Classifier: License :: OSI Approved :: MIT License
Classifier: Operating System :: OS Independent
Classifier: Programming Language :: Python
Classifier: Programming Language :: Python :: 3
Classifier: Topic :: Software Development :: Libraries :: Python Modules
Requires-Python: >=3.6
Provides-Extra: domainapi
Provides-Extra: docker
